[
    {
        "id": 1,
        "title": "Лабораторная 4",
        "description": "Диаграмма UML Use Case",
        "preview": "https://yandex.ru/images/search?text=фото&from=tabbar&pos=9&img_url=https%3A%2F%2Fwww.gearmerchant.ru%2Fimg%2Fproducts%2F22410-babcock-gosudarstvennyj-park-poljane-creek-mukomolnoj-melnicy-kc850-gostinoj-doma-steny-sovremennogo-iskusstva-dekor-derevjannoj-rame-tkan-plakaty-pechati.jpg&rpt=simage"
    },
    {
        "id": 2,
        "title": "Лабораторная 5",
        "description": "Диаграмма UML Class",
        "preview": "https://github.com/imoldobaew/moldobaew-page/blob/master/img/ERD%20Class.png?raw=true"
    },
     {
        "id": 3,
        "title": "Лабораторная 6",
        "description": "Диаграмма UML Sequence",
        "preview": "/img/UML%20Sequence.png"
    },
     {
        "id": 4,
        "title": "Лабораторная 7",
        "description": "Диаграмма UML Component",
        "preview": "/img/UML%20Component.png"
    }
]
